{"cameraMode":{"drawMode":0,"name":"Shaded","section":"Shading Mode"},"sceneLighting":true,"audioPlay":false,"sceneViewState":{"m_AlwaysRefresh":false,"showFog":true,"showSkybox":true,"showFlares":true,"showImageEffects":true,"showParticleSystems":true,"showVisualEffectGraphs":true,"m_FxEnabled":true},"in2DMode":false,"pivot":{"x":-13.354148864746094,"y":-11.021190643310547,"z":31.065052032470704},"rotation":{"x":0.256123423576355,"y":-0.15519343316555024,"z":0.041700687259435657,"w":0.9531936645507813},"size":13.937034606933594,"orthographic":false}